pytest_error.py
pytest_error-0.1.1.dist-info/METADATA
pytest_error-0.1.1.dist-info/WHEEL
pytest_error-0.1.1.dist-info/RECORD
