Metadata-Version: 2.4
Name: pytest-error
Version: 0.1.1
Summary: A decorator for testing exceptions with pytest
License-Expression: MIT
Keywords: pytest,testing,exception,error,error message
Author: Jonathan King
Author-email: jonking93@gmail.com
Maintainer: Jonathan King
Maintainer-email: jonking93@gmail.com
Requires-Python: >=3.10, <4.0
Classifier: Development Status :: 4 - Beta
Classifier: Framework :: Pytest
Classifier: Intended Audience :: Developers
Classifier: Topic :: Software Development :: Testing
Classifier: License :: OSI Approved :: MIT License
Classifier: Operating System :: OS Independent
Classifier: Programming Language :: Python
Classifier: Programming Language :: Python :: 3 :: Only
Classifier: Programming Language :: Python :: 3.10
Classifier: Programming Language :: Python :: 3.11
Classifier: Programming Language :: Python :: 3.12
Classifier: Programming Language :: Python :: 3.13
Classifier: Programming Language :: Python :: 3.14
Requires-Dist: pytest (>=8.4)
Project-URL: Documentation, https://jonking93.github.io/pytest-error
Project-URL: Repository, https://github.com/pytest-error
